embodyfile/__init__.py
embodyfile/__main__.py
embodyfile/cli.py
embodyfile/embodyfile.py
embodyfile/export_utils.py
embodyfile/formatters.py
embodyfile/logging.py
embodyfile/models.py
embodyfile/parser.py
embodyfile/parser_utils.py
embodyfile/py.typed
embodyfile/schemas.py
embodyfile/exporters/__init__.py
embodyfile/exporters/common.py
embodyfile/exporters/csv_exporter.py
embodyfile/exporters/hdf_exporter.py
embodyfile/exporters/hdf_legacy_exporter.py
embodyfile/exporters/parquet_exporter.py
embody_file-1.0.34.dist-info/METADATA
embody_file-1.0.34.dist-info/WHEEL
embody_file-1.0.34.dist-info/entry_points.txt
embody_file-1.0.34.dist-info/licenses/LICENSE
embody_file-1.0.34.dist-info/RECORD
