Metadata-Version: 2.4
Name: embody-file
Version: 1.0.34
Summary: Embody file converter
Project-URL: Homepage, https://github.com/aidee-health/embody-file
Project-URL: Repository, https://github.com/aidee-health/embody-file
Project-URL: Changelog, https://github.com/aidee-health/embody-file/releases
Author-email: Aidee Health <hello@aidee.io>
License-Expression: MIT
License-File: LICENSE
Classifier: Development Status :: 5 - Production/Stable
Requires-Python: <4.0,>=3.11
Requires-Dist: embody-codec>=1.0.32
Requires-Dist: pandas>=1.5.1
Requires-Dist: pyarrow<20,>=19.0.1
Requires-Dist: pytz<2026.0,>=2024.1
Requires-Dist: tables<4,>=3.10.2
